LICENSE
MANIFEST.in
README.md
pyproject.toml
requirements.txt
setup.py
google_scholar_py/__init__.py
google_scholar_py/custom_backend/author_info_all_articles.py
google_scholar_py/custom_backend/cite_results.py
google_scholar_py/custom_backend/google_scholar_cited_by_public_access_author.py
google_scholar_py/custom_backend/organic_search.py
google_scholar_py/custom_backend/profiles_results.py
google_scholar_py/custom_backend/top_mandates_metrics.py
google_scholar_py/custom_backend/top_publications_article.py
google_scholar_py/custom_backend/top_publications_article_citation.py
google_scholar_py/custom_backend/top_publications_metrics.py
google_scholar_py/serpapi_backend/author_results.py
google_scholar_py/serpapi_backend/organic_cite_results.py
google_scholar_py/serpapi_backend/organic_results.py
google_scholar_py/serpapi_backend/profile_results.py
scrape_google_scholar_py.egg-info/PKG-INFO
scrape_google_scholar_py.egg-info/SOURCES.txt
scrape_google_scholar_py.egg-info/dependency_links.txt
scrape_google_scholar_py.egg-info/requires.txt
scrape_google_scholar_py.egg-info/top_level.txt