Metadata-Version: 2.1
Name: scrape-google-scholar-py
Version: 0.3.4
Summary: Extract data from all Google Scholar pages in Python. Sponsored by SerpApi.
Home-page: https://github.com/dimitryzub/scrape-google-scholar
Author: Dmitiry Zub
Author-email: dimitryzub@gmail.com
Maintainer: Dmitiry Zub
Maintainer-email: dimitryzub@gmail.com
License: MIT
Project-URL: Documentation, https://github.com/dimitryzub/scrape-google-scholar#example-usage-custom-backend
Project-URL: Source, https://github.com/dimitryzub/scrape-google-scholar
Project-URL: Tracker, https://github.com/dimitryzub/scrape-google-scholar/issues
Keywords: google scholar,serpapi,scraper,python,python google scholar,python google scholar api,web scraping,python web scraping,research,lexbor,selectolax,selenium,selenium-stealth,pandas
Classifier: Development Status :: 3 - Alpha
Classifier: Intended Audience :: Developers
Classifier: Operating System :: Microsoft :: Windows
Classifier: Operating System :: MacOS
Classifier: Operating System :: POSIX :: Linux
Classifier: Topic :: Internet
Classifier: Natural Language :: English
Classifier: Topic :: Utilities
Classifier: Programming Language :: Python :: 3.10
Classifier: Programming Language :: Python :: 3.11
Requires-Python: >=3.10
License-File: LICENSE
